{
  "boards": [
    {
      "name": "Кося",
      "id": 1
    },
    {
      "name": "Жорик",
      "id": 2
    },
    {
      "name": "Алеся",
      "id": 3
    }
  ],
  "lists": [
    {
      "boardId": 1,
      "name": "Понедельник",
      "id": 1
    },
    {
      "boardId": 1,
      "name": "Вторник",
      "id": 2
    },
    {
      "boardId": 2,
      "name": "Понедельник",
      "id": 3
    },
    {
      "boardId": 1,
      "name": "Среда",
      "id": 4
    },
    {
      "boardId": 2,
      "name": "Вторник",
      "id": 5
    },
    {
      "boardId": 1,
      "name": "Четверг",
      "id": 6
    },
    {
      "boardId": 1,
      "name": "Пятница",
      "id": 7
    },
    {
      "boardId": 3,
      "name": "Понедельник",
      "id": 8
    }
  ],
  "elements": [
    {
      "listId": 1,
      "content": "Поспать",
      "isChecked": true,
      "position": 2,
      "id": 1
    },
    {
      "listId": 1,
      "content": "Покекать",
      "isChecked": true,
      "position": 1,
      "id": 2
    },
    {
      "listId": 4,
      "content": "Похехекать",
      "isChecked": false,
      "position": 1,
      "id": 3
    },
    {
      "listId": 2,
      "content": "Поспать",
      "isChecked": false,
      "position": 1,
      "id": 4
    }
  ]
}